{
  "dist-tags": {
    "latest": "2.0.9"
  },
  "versions": {
    "2.0.10": {
      "name": "com.unity.toolchain.win-x86_64-linux-x86_64",
      "version": "2.0.10",
      "displayName": "Toolchain Win Linux x64",
      "description": "Cross-compilation toolchain to build player target Linux x86_64 on host Windows x86_64",
      "keywords": [
        "toolchain",
        "windows",
        "linux",
        "cross-compilation"
      ],
      "dependencies": {
        "com.unity.sysroot": "2.0.10",
        "com.unity.sysroot.linux-x86_64": "2.0.9"
      },
      "documentationUrl": "https://docs.unity3d.com/Packages/com.unity.toolchain.win-x86_64-linux-x86_64@2.0/manual/index.html",
      "unity": "2019.4",
      "dist": {
        "shasum": "426618737602d0ff76e85db678b73b56aa2e891a",
        "tarball": "https://download-packages.unity.cn/com.unity.toolchain.win-x86_64-linux-x86_64/-/com.unity.toolchain.win-x86_64-linux-x86_64-2.0.10.tgz"
      },
      "_upm": {
        "changelog": "Optimized and reduced package size"
      }
    },
    "2.0.9": {
      "name": "com.unity.toolchain.win-x86_64-linux-x86_64",
      "version": "2.0.9",
      "displayName": "Toolchain Win Linux x64",
      "description": "Cross-compilation toolchain to build player target Linux x86_64 on host Windows x86_64",
      "keywords": [
        "toolchain",
        "windows",
        "linux",
        "cross-compilation"
      ],
      "category": "",
      "dependencies": {
        "com.unity.sysroot": "2.0.10",
        "com.unity.sysroot.linux-x86_64": "2.0.9"
      },
      "unity": "2019.4",
      "_upm": {
        "changelog": "Updated to Clang 9.0.1"
      },
      "upmCi": {
        "footprint": "716df06c30c8556773adf3eb3ff9431ec1fc0e7c"
      },
      "documentationUrl": "https://docs.unity3d.com/Packages/com.unity.toolchain.win-x86_64-linux-x86_64@2.0/manual/index.html",
      "repository": {
        "url": "https://github.com/Unity-Technologies/com.unity.sysroot.git",
        "type": "git",
        "revision": "bf7a008256a1175e0f8a0d7d26d6826cbfbe1bb2"
      },
      "dist": {
        "shasum": "22f622e0821fc835034e57944ff152a3049178fe",
        "tarball": "https://download-packages.unity.cn/com.unity.toolchain.win-x86_64-linux-x86_64/-/com.unity.toolchain.win-x86_64-linux-x86_64-2.0.9.tgz"
      }
    },
    "2.0.6": {
      "name": "com.unity.toolchain.win-x86_64-linux-x86_64",
      "version": "2.0.6",
      "displayName": "Toolchain Win Linux x64",
      "description": "Cross-compilation toolchain to build player target Linux x86_64 on host Windows x86_64",
      "keywords": [
        "toolchain",
        "windows",
        "linux",
        "cross-compilation"
      ],
      "category": "",
      "dependencies": {
        "com.unity.sysroot": "2.0.7",
        "com.unity.sysroot.linux-x86_64": "2.0.6"
      },
      "unity": "2019.4",
      "_upm": {
        "changelog": "bump version number to publish"
      },
      "upmCi": {
        "footprint": "f0ceefcaaa04beae77991f731fdd823465e81f24"
      },
      "documentationUrl": "https://docs.unity3d.com/Packages/com.unity.toolchain.win-x86_64-linux-x86_64@2.0/manual/index.html",
      "repository": {
        "url": "https://github.com/Unity-Technologies/com.unity.sysroot.git",
        "type": "git",
        "revision": "bf00578d8ff96f17f95a226bb361b69fe2860cc1"
      },
      "dist": {
        "shasum": "1366883a1868f29a10a1d2d6d6d09e4016aa5a77",
        "tarball": "https://download-packages.unity.cn/com.unity.toolchain.win-x86_64-linux-x86_64/-/com.unity.toolchain.win-x86_64-linux-x86_64-2.0.6.tgz"
      }
    },
    "2.0.5": {
      "name": "com.unity.toolchain.win-x86_64-linux-x86_64",
      "version": "2.0.5",
      "displayName": "Toolchain Win Linux x64",
      "description": "Cross-compilation toolchain to build player target Linux x86_64 on host Windows x86_64",
      "keywords": [
        "toolchain",
        "windows",
        "linux",
        "cross-compilation"
      ],
      "category": "",
      "dependencies": {
        "com.unity.sysroot": "2.0.6",
        "com.unity.sysroot.linux-x86_64": "2.0.5"
      },
      "unity": "2019.4",
      "_upm": {
        "changelog": "bump version number to publish"
      },
      "upmCi": {
        "footprint": "a7a14a28c52da15f406c8dc13ac0d3986a372bb3"
      },
      "documentationUrl": "https://docs.unity3d.com/Packages/com.unity.toolchain.win-x86_64-linux-x86_64@2.0/manual/index.html",
      "repository": {
        "url": "https://github.com/Unity-Technologies/com.unity.sysroot.git",
        "type": "git",
        "revision": "51a7fbe63b09f6d0f31f346c0758152899a52668"
      },
      "dist": {
        "shasum": "cf06a9c5383ee100a5cb003a7a5033a69894d330",
        "tarball": "https://download-packages.unity.cn/com.unity.toolchain.win-x86_64-linux-x86_64/-/com.unity.toolchain.win-x86_64-linux-x86_64-2.0.5.tgz"
      }
    },
    "2.0.4": {
      "name": "com.unity.toolchain.win-x86_64-linux-x86_64",
      "version": "2.0.4",
      "displayName": "Toolchain Win Linux x64",
      "description": "Cross-compilation toolchain to build player target Linux x86_64 on host Windows x86_64",
      "keywords": [
        "toolchain",
        "windows",
        "linux",
        "cross-compilation"
      ],
      "category": "",
      "dependencies": {
        "com.unity.sysroot": "2.0.5",
        "com.unity.sysroot.linux-x86_64": "2.0.4"
      },
      "unity": "2019.4",
      "upmCi": {
        "footprint": "21cf819dbf560aec681fa3b1bcdf4b76ece5e02e"
      },
      "documentationUrl": "https://docs.unity3d.com/Packages/com.unity.toolchain.win-x86_64-linux-x86_64@2.0/manual/index.html",
      "repository": {
        "url": "https://github.com/Unity-Technologies/com.unity.sysroot.git",
        "type": "git",
        "revision": "06af5d019fed618daef07b5db278be147aed574b"
      },
      "dist": {
        "shasum": "3e2bb89d333716e768ae6c6cb861407679a6e73e",
        "tarball": "https://download-packages.unity.cn/com.unity.toolchain.win-x86_64-linux-x86_64/-/com.unity.toolchain.win-x86_64-linux-x86_64-2.0.4.tgz"
      }
    },
    "2.0.3": {
      "name": "com.unity.toolchain.win-x86_64-linux-x86_64",
      "version": "2.0.3",
      "displayName": "Toolchain Win Linux x64",
      "description": "Cross-compilation toolchain to build player target Linux x86_64 on host Windows x86_64",
      "keywords": [
        "toolchain",
        "windows",
        "linux",
        "cross-compilation"
      ],
      "category": "",
      "dependencies": {
        "com.unity.sysroot": "2.0.4",
        "com.unity.sysroot.linux-x86_64": "2.0.3"
      },
      "unity": "2019.4",
      "upmCi": {
        "footprint": "b1589562e58283344d9b923fe976904ef41a514c"
      },
      "repository": {
        "url": "https://github.com/Unity-Technologies/com.unity.sysroot.git",
        "type": "git",
        "revision": "573e391bf0f49bc3cce1c2eea80944b240187feb"
      },
      "dist": {
        "shasum": "5a9db761457d3f514ee2d2fde46beb901505d221",
        "tarball": "https://download-packages.unity.cn/com.unity.toolchain.win-x86_64-linux-x86_64/-/com.unity.toolchain.win-x86_64-linux-x86_64-2.0.3.tgz"
      }
    },
    "2.0.2": {
      "name": "com.unity.toolchain.win-x86_64-linux-x86_64",
      "version": "2.0.2",
      "displayName": "Toolchain Win Linux x64",
      "description": "Cross-compilation toolchain to build player target Linux x86_64 on host Windows x86_64",
      "keywords": [
        "toolchain",
        "windows",
        "linux",
        "cross-compilation"
      ],
      "category": "",
      "dependencies": {
        "com.unity.sysroot": "2.0.3",
        "com.unity.sysroot.linux-x86_64": "2.0.2"
      },
      "unity": "2019.4",
      "_upm": {
        "changelog": "bump version number to publish"
      },
      "upmCi": {
        "footprint": "35d2b185853ea3f36b9475c13fbe313a7cfee98e"
      },
      "repository": {
        "url": "https://github.com/Unity-Technologies/com.unity.sysroot.git",
        "type": "git",
        "revision": "66ed41bba76e1f66c4e578e9bad86d33dff8b82b"
      },
      "_id": "com.unity.toolchain.win-x86_64-linux-x86_64@2.0.2",
      "_integrity": "sha512-F3Sctu2s0tTnxpGsamYN6W7L8hd/hH9eFbq4bmpxsb3Erf6kYoqerIbf9cj9iGoxlaUnEN0WDx5kkOe/ih+GIA==",
      "_resolved": "/tmp/com.unity.toolchain.win-x86_64-linux-x86_64@2.0.2-yqbwo9ms.tgz",
      "_from": "file:/tmp/com.unity.toolchain.win-x86_64-linux-x86_64@2.0.2-yqbwo9ms.tgz",
      "dist": {
        "shasum": "18b88705277e5a00e00740e3e7bde171a7135bfa",
        "tarball": "https://download-packages.unity.cn/com.unity.toolchain.win-x86_64-linux-x86_64/-/com.unity.toolchain.win-x86_64-linux-x86_64-2.0.2.tgz"
      }
    },
    "2.0.1": {
      "name": "com.unity.toolchain.win-x86_64-linux-x86_64",
      "version": "2.0.1",
      "displayName": "Toolchain Win Linux x64",
      "description": "Cross-compilation toolchain to build player target Linux x86_64 on host Windows x86_64",
      "keywords": [
        "toolchain",
        "windows",
        "linux",
        "cross-compilation"
      ],
      "category": "",
      "dependencies": {
        "com.unity.sysroot": "2.0.2",
        "com.unity.sysroot.linux-x86_64": "2.0.1"
      },
      "unity": "2019.4",
      "_upm": {
        "changelog": "bump version number to publish"
      },
      "upmCi": {
        "footprint": "cef86953fc8bb095c7759221b671969e91e13aa6"
      },
      "repository": {
        "url": "https://github.com/Unity-Technologies/com.unity.sysroot.git",
        "type": "git",
        "revision": "79ad97256e4e2cbdfac64dec6ee1932a5c3aeacc"
      },
      "_id": "com.unity.toolchain.win-x86_64-linux-x86_64@2.0.1",
      "_integrity": "sha512-4Iw0BD6akrKjzuHIYZo0ovl9H/8u3rJh+nWBo5QqJQ6QqQLjM2nHQZY4B1kiaSHtReOi0ZW1AEyxq4EOLpo+Gw==",
      "_resolved": "/tmp/com.unity.toolchain.win-x86_64-linux-x86_64@2.0.1-p5_2yfnz.tgz",
      "_from": "file:/tmp/com.unity.toolchain.win-x86_64-linux-x86_64@2.0.1-p5_2yfnz.tgz",
      "dist": {
        "shasum": "578279576a9d01a8d9b6b617241bad758e127f00",
        "tarball": "https://download-packages.unity.cn/com.unity.toolchain.win-x86_64-linux-x86_64/-/com.unity.toolchain.win-x86_64-linux-x86_64-2.0.1.tgz"
      }
    },
    "2.0.0": {
      "name": "com.unity.toolchain.win-x86_64-linux-x86_64",
      "version": "2.0.0",
      "displayName": "Toolchain Win Linux x64",
      "description": "Cross-compilation toolchain to build player target Linux x86_64 on host Windows x86_64",
      "keywords": [
        "toolchain",
        "windows",
        "linux",
        "cross-compilation"
      ],
      "category": "",
      "dependencies": {
        "com.unity.sysroot": "2.0.0",
        "com.unity.sysroot.linux-x86_64": "2.0.0"
      },
      "unity": "2019.4",
      "upm": {
        "changelog": "- Fix 1336012 - Build from windows fails if username contains space\r\n- Add support for new IL2CPP arguments APIs"
      },
      "upmCi": {
        "footprint": "a544e6b1225ea258dabb6b6be43a88eeb880a95d"
      },
      "repository": {
        "url": "https://github.com/Unity-Technologies/com.unity.sysroot.git",
        "type": "git",
        "revision": "e6c53e52ad77e8d1a6cfc2707e348f9e4799c595"
      },
      "_id": "com.unity.toolchain.win-x86_64-linux-x86_64@2.0.0",
      "_integrity": "sha512-BH8gqDgTkr43UrmCcAmH047oQnjgK90k82xwVC+8VvUjyJRd8egHWXn4/oD7UXl8dBhMcxELgmW17ShM+B/PvQ==",
      "_resolved": "/tmp/com.unity.toolchain.win-x86_64-linux-x86_64@2.0.0-ivz9ajcb.tgz",
      "_from": "file:/tmp/com.unity.toolchain.win-x86_64-linux-x86_64@2.0.0-ivz9ajcb.tgz",
      "dist": {
        "shasum": "a25d848cbdc1e0886ace466bc4d6b8f5b6659ade",
        "tarball": "https://download-packages.unity.cn/com.unity.toolchain.win-x86_64-linux-x86_64/-/com.unity.toolchain.win-x86_64-linux-x86_64-2.0.0.tgz"
      }
    },
    "1.0.0": {
      "name": "com.unity.toolchain.win-x86_64-linux-x86_64",
      "version": "1.0.0",
      "displayName": "Toolchain Win Linux x64",
      "description": "Cross-compilation toolchain to build player target Linux x86_64 on host Windows x86_64",
      "keywords": [
        "toolchain",
        "windows",
        "linux",
        "cross-compilation"
      ],
      "category": "",
      "dependencies": {
        "com.unity.sysroot": "1.0.0",
        "com.unity.sysroot.linux-x86_64": "1.0.0"
      },
      "unity": "2019.3",
      "upmCi": {
        "footprint": "6753d5f80bec773cf8653f169d229be31e56c4b9"
      },
      "repository": {
        "url": "https://github.com/Unity-Technologies/com.unity.sysroot.git",
        "type": "git",
        "revision": "0b6b1770930fd9a6c9365613ff2cba3eb81810dd"
      },
      "_id": "com.unity.toolchain.win-x86_64-linux-x86_64@1.0.0",
      "_integrity": "sha512-Yz3PJgzyF0aiamiSkCSUN/6vFDFD+iHQlxl10/zSkSDrmAmiImlfqB1Covutsdg3V71/FZjglzo5jxr3rTYqrA==",
      "_resolved": "/pkgprom/com.unity.toolchain.win-x86_64-linux-x86_64-1.0.0.tgz",
      "_from": "file:com.unity.toolchain.win-x86_64-linux-x86_64-1.0.0.tgz",
      "dist": {
        "shasum": "24431453da4e1af56b8c4d4b73534f78717031a6",
        "tarball": "https://download-packages.unity.cn/com.unity.toolchain.win-x86_64-linux-x86_64/-/com.unity.toolchain.win-x86_64-linux-x86_64-1.0.0.tgz"
      }
    },
    "0.1.21-preview": {
      "name": "com.unity.toolchain.win-x86_64-linux-x86_64",
      "version": "0.1.21-preview",
      "displayName": "Toolchain Win Linux x64",
      "description": "Cross-compilation toolchain to build player target Linux x86_64 on host Windows x86_64",
      "keywords": [
        "toolchain",
        "windows",
        "linux",
        "cross-compilation"
      ],
      "category": "",
      "dependencies": {
        "com.unity.sysroot": "0.1.19-preview",
        "com.unity.sysroot.linux-x86_64": "0.1.14-preview"
      },
      "unity": "2019.3",
      "upmCi": {
        "footprint": "14796f91b701057c14c402b84507c4e7491f8744"
      },
      "repository": {
        "url": "git+https://github.com/Unity-Technologies/com.unity.sysroot.git",
        "type": "git",
        "revision": "c23b9fb202dceb7b518aa7353d96a3e2eae227c5"
      },
      "_resolved": "",
      "_integrity": "",
      "_from": "file:com.unity.toolchain.win-x86_64-linux-x86_64-0.1.21-preview.tgz",
      "readmeFilename": "README.md",
      "bugs": {
        "url": "https://github.com/Unity-Technologies/com.unity.sysroot/issues"
      },
      "homepage": "https://github.com/Unity-Technologies/com.unity.sysroot#readme",
      "_id": "com.unity.toolchain.win-x86_64-linux-x86_64@0.1.21-preview",
      "dist": {
        "shasum": "c9e25f7e3655d484578e0a41b76bf9c827cd2d28",
        "tarball": "https://download-packages.unity.cn/com.unity.toolchain.win-x86_64-linux-x86_64/-/com.unity.toolchain.win-x86_64-linux-x86_64-0.1.21-preview.tgz"
      }
    },
    "0.1.20-preview": {
      "name": "com.unity.toolchain.win-x86_64-linux-x86_64",
      "version": "0.1.20-preview",
      "displayName": "Toolchain Win Linux x64",
      "description": "Cross-compilation toolchain to build player target Linux x86_64 on host Windows x86_64",
      "keywords": [
        "toolchain",
        "windows",
        "linux",
        "cross-compilation"
      ],
      "category": "",
      "dependencies": {
        "com.unity.sysroot": "0.1.19-preview",
        "com.unity.sysroot.linux-x86_64": "0.1.14-preview"
      },
      "unity": "2019.3",
      "upmCi": {
        "footprint": "8adf863e403c603de51bd76c1b8f93097915d278"
      },
      "repository": {
        "url": "git+https://github.com/Unity-Technologies/com.unity.sysroot.git",
        "type": "git",
        "revision": "7c94a58243a9e8b0a1375dff9e0ab89b630766be"
      },
      "_resolved": "",
      "_integrity": "",
      "_from": "file:com.unity.toolchain.win-x86_64-linux-x86_64-0.1.20-preview.tgz",
      "readmeFilename": "README.md",
      "bugs": {
        "url": "https://github.com/Unity-Technologies/com.unity.sysroot/issues"
      },
      "homepage": "https://github.com/Unity-Technologies/com.unity.sysroot#readme",
      "_id": "com.unity.toolchain.win-x86_64-linux-x86_64@0.1.20-preview",
      "dist": {
        "shasum": "b731d6a982644efc085397bc7cdf0650ac539bb0",
        "tarball": "https://download-packages.unity.cn/com.unity.toolchain.win-x86_64-linux-x86_64/-/com.unity.toolchain.win-x86_64-linux-x86_64-0.1.20-preview.tgz"
      }
    },
    "0.1.19-preview": {
      "name": "com.unity.toolchain.win-x86_64-linux-x86_64",
      "version": "0.1.19-preview",
      "displayName": "Toolchain Win Linux x64",
      "description": "Cross-compilation toolchain to build player target Linux x86_64 on host Windows x86_64",
      "keywords": [
        "toolchain",
        "windows",
        "linux",
        "cross-compilation"
      ],
      "category": "",
      "dependencies": {
        "com.unity.sysroot": "0.1.19-preview",
        "com.unity.sysroot.linux-x86_64": "0.1.14-preview"
      },
      "unity": "2019.3",
      "upmCi": {
        "footprint": "048f85c988283c16b1d6536c1d6e2b5c0b9cefea"
      },
      "repository": {
        "url": "git+https://github.com/Unity-Technologies/com.unity.sysroot.git",
        "type": "git",
        "revision": "8717ab9c5b4f758bc542184e1872ed3fcce1e1f9"
      },
      "_resolved": "",
      "_integrity": "",
      "_from": "file:com.unity.toolchain.win-x86_64-linux-x86_64-0.1.19-preview.tgz",
      "readmeFilename": "README.md",
      "bugs": {
        "url": "https://github.com/Unity-Technologies/com.unity.sysroot/issues"
      },
      "homepage": "https://github.com/Unity-Technologies/com.unity.sysroot#readme",
      "_id": "com.unity.toolchain.win-x86_64-linux-x86_64@0.1.19-preview",
      "dist": {
        "shasum": "287a551e914f09dc4764f23929b91eb2269448bb",
        "tarball": "https://download-packages.unity.cn/com.unity.toolchain.win-x86_64-linux-x86_64/-/com.unity.toolchain.win-x86_64-linux-x86_64-0.1.19-preview.tgz"
      }
    },
    "0.1.18-preview": {
      "name": "com.unity.toolchain.win-x86_64-linux-x86_64",
      "version": "0.1.18-preview",
      "displayName": "Toolchain Win Linux x64",
      "description": "Cross-compilation toolchain to build player target Linux x86_64 on host Windows x86_64",
      "keywords": [
        "toolchain",
        "windows",
        "linux",
        "cross-compilation"
      ],
      "category": "",
      "dependencies": {
        "com.unity.sysroot": "0.1.18-preview",
        "com.unity.sysroot.linux-x86_64": "0.1.14-preview"
      },
      "unity": "2019.3",
      "upmCi": {
        "footprint": "b3bc8a559f827946fa0fea5936f46a6b56232404"
      },
      "repository": {
        "url": "git+https://github.com/Unity-Technologies/com.unity.sysroot.git",
        "type": "git",
        "revision": "0d5e7b07c95f3ae15d6d80931a071b042e97189b"
      },
      "_resolved": "",
      "_integrity": "",
      "_from": "file:com.unity.toolchain.win-x86_64-linux-x86_64-0.1.18-preview.tgz",
      "readmeFilename": "README.md",
      "bugs": {
        "url": "https://github.com/Unity-Technologies/com.unity.sysroot/issues"
      },
      "homepage": "https://github.com/Unity-Technologies/com.unity.sysroot#readme",
      "_id": "com.unity.toolchain.win-x86_64-linux-x86_64@0.1.18-preview",
      "dist": {
        "shasum": "db936ef342d43d039fd8e4ae78e987fd0fab6e77",
        "tarball": "https://download-packages.unity.cn/com.unity.toolchain.win-x86_64-linux-x86_64/-/com.unity.toolchain.win-x86_64-linux-x86_64-0.1.18-preview.tgz"
      }
    },
    "0.1.17-preview": {
      "name": "com.unity.toolchain.win-x86_64-linux-x86_64",
      "version": "0.1.17-preview",
      "displayName": "Toolchain Win Linux x64",
      "description": "Cross-compilation toolchain to build player target Linux x86_64 on host Windows x86_64",
      "keywords": [
        "toolchain",
        "windows",
        "linux",
        "cross-compilation"
      ],
      "category": "",
      "dependencies": {
        "com.unity.sysroot": "0.1.17-preview",
        "com.unity.sysroot.linux-x86_64": "0.1.13-preview"
      },
      "unity": "2019.3",
      "upmCi": {
        "footprint": "932ec27618c0d36515cd960161a486a54212f013"
      },
      "repository": {
        "url": "git+https://github.com/Unity-Technologies/com.unity.sysroot.git",
        "type": "git",
        "revision": "e75358d77f4b449b986678c1bceb41ad151d99be"
      },
      "_resolved": "",
      "_integrity": "",
      "_from": "file:com.unity.toolchain.win-x86_64-linux-x86_64-0.1.17-preview.tgz",
      "readmeFilename": "README.md",
      "bugs": {
        "url": "https://github.com/Unity-Technologies/com.unity.sysroot/issues"
      },
      "homepage": "https://github.com/Unity-Technologies/com.unity.sysroot#readme",
      "_id": "com.unity.toolchain.win-x86_64-linux-x86_64@0.1.17-preview",
      "dist": {
        "shasum": "722c2d9b4412f26d965245843e3e6545234f6025",
        "tarball": "https://download-packages.unity.cn/com.unity.toolchain.win-x86_64-linux-x86_64/-/com.unity.toolchain.win-x86_64-linux-x86_64-0.1.17-preview.tgz"
      }
    },
    "0.1.16-preview": {
      "name": "com.unity.toolchain.win-x86_64-linux-x86_64",
      "version": "0.1.16-preview",
      "displayName": "Toolchain Win Linux x64",
      "description": "Cross-compilation toolchain to build player target Linux x86_64 on host Windows x86_64",
      "keywords": [
        "toolchain",
        "windows",
        "linux",
        "cross-compilation"
      ],
      "category": "",
      "dependencies": {
        "com.unity.sysroot": "0.1.16-preview",
        "com.unity.sysroot.linux-x86_64": "0.1.12-preview"
      },
      "unity": "2019.3",
      "upmCi": {
        "footprint": "c5f37ca3b8fea4463de75a4fcc4e05ade7f34c2a"
      },
      "repository": {
        "url": "git+https://github.com/Unity-Technologies/com.unity.sysroot.git",
        "type": "git",
        "revision": "ff1539e86bf56630844f67c5eb2548578a433e33"
      },
      "_resolved": "",
      "_integrity": "",
      "_from": "file:com.unity.toolchain.win-x86_64-linux-x86_64-0.1.16-preview.tgz",
      "readmeFilename": "README.md",
      "bugs": {
        "url": "https://github.com/Unity-Technologies/com.unity.sysroot/issues"
      },
      "homepage": "https://github.com/Unity-Technologies/com.unity.sysroot#readme",
      "_id": "com.unity.toolchain.win-x86_64-linux-x86_64@0.1.16-preview",
      "dist": {
        "shasum": "96db189bc7e78943af388b80acef6733abec7af9",
        "tarball": "https://download-packages.unity.cn/com.unity.toolchain.win-x86_64-linux-x86_64/-/com.unity.toolchain.win-x86_64-linux-x86_64-0.1.16-preview.tgz"
      }
    },
    "0.1.15-preview": {
      "name": "com.unity.toolchain.win-x86_64-linux-x86_64",
      "version": "0.1.15-preview",
      "displayName": "Toolchain Win Linux x64",
      "description": "Cross-compilation toolchain to build player target Linux x86_64 on host Windows x86_64",
      "keywords": [
        "toolchain",
        "windows",
        "linux",
        "cross-compilation"
      ],
      "category": "",
      "dependencies": {
        "com.unity.sysroot": "0.1.15-preview",
        "com.unity.sysroot.linux-x86_64": "0.1.11-preview"
      },
      "unity": "2019.3",
      "upmCi": {
        "footprint": "91b19bae0f78d227b81e9e7bda1e9fb97b90ef1c"
      },
      "repository": {
        "url": "git+https://github.com/Unity-Technologies/com.unity.sysroot.git",
        "type": "git",
        "revision": "e39e4a088457f7e32424ae26effff65208c3c9a2"
      },
      "_resolved": "",
      "_integrity": "",
      "_from": "file:com.unity.toolchain.win-x86_64-linux-x86_64-0.1.15-preview.tgz",
      "readmeFilename": "README.md",
      "bugs": {
        "url": "https://github.com/Unity-Technologies/com.unity.sysroot/issues"
      },
      "homepage": "https://github.com/Unity-Technologies/com.unity.sysroot#readme",
      "_id": "com.unity.toolchain.win-x86_64-linux-x86_64@0.1.15-preview",
      "dist": {
        "shasum": "05d8af27a0f02a5e05910d63aa1eaecc4980976f",
        "tarball": "https://download-packages.unity.cn/com.unity.toolchain.win-x86_64-linux-x86_64/-/com.unity.toolchain.win-x86_64-linux-x86_64-0.1.15-preview.tgz"
      }
    },
    "0.1.14-preview": {
      "name": "com.unity.toolchain.win-x86_64-linux-x86_64",
      "version": "0.1.14-preview",
      "displayName": "Toolchain Win Linux x64",
      "description": "Cross-compilation toolchain to build player target Linux x86_64 on host Windows x86_64",
      "keywords": [
        "toolchain",
        "windows",
        "linux",
        "cross-compilation"
      ],
      "category": "",
      "dependencies": {
        "com.unity.sysroot": "0.1.14-preview",
        "com.unity.sysroot.linux-x86_64": "0.1.10-preview"
      },
      "unity": "2019.3",
      "author": {
        "name": "Unity Technologies Inc.",
        "url": "https://www.unity3d.com"
      },
      "upmCi": {
        "footprint": "df7b75f6224dc424f9a6cb7d784bc66e027d789f"
      },
      "repository": {
        "url": "git+https://github.com/Unity-Technologies/com.unity.sysroot.git",
        "type": "git",
        "revision": "8230af92545c409f56d007e86fe15cc109bfbd53"
      },
      "_resolved": "",
      "_integrity": "",
      "_from": "file:com.unity.toolchain.win-x86_64-linux-x86_64-0.1.14-preview.tgz",
      "readmeFilename": "README.md",
      "bugs": {
        "url": "https://github.com/Unity-Technologies/com.unity.sysroot/issues"
      },
      "homepage": "https://github.com/Unity-Technologies/com.unity.sysroot#readme",
      "_id": "com.unity.toolchain.win-x86_64-linux-x86_64@0.1.14-preview",
      "dist": {
        "shasum": "e36a11e0151ba48e07916659902dc8d9c7c9e407",
        "tarball": "https://download-packages.unity.cn/com.unity.toolchain.win-x86_64-linux-x86_64/-/com.unity.toolchain.win-x86_64-linux-x86_64-0.1.14-preview.tgz"
      }
    },
    "0.1.13-preview": {
      "name": "com.unity.toolchain.win-x86_64-linux-x86_64",
      "version": "0.1.13-preview",
      "displayName": "Toolchain Win Linux x64",
      "description": "Cross-compilation toolchain to build player target Linux x86_64 on host Windows x86_64",
      "keywords": [
        "toolchain",
        "windows",
        "linux",
        "cross-compilation"
      ],
      "category": "",
      "dependencies": {
        "com.unity.sysroot": "0.1.14-preview",
        "com.unity.sysroot.linux-x86_64": "0.1.10-preview"
      },
      "unity": "2019.3",
      "author": {
        "name": "Unity Technologies Inc.",
        "url": "https://www.unity3d.com"
      },
      "upmCi": {
        "footprint": "afe5d5fc43e167225b6b43a36b106aaac1eef066"
      },
      "repository": {
        "url": "git+https://github.com/Unity-Technologies/com.unity.sysroot.git",
        "type": "git",
        "revision": "50b119182aa2fd6c8f469d5917c5dfe4371f4986"
      },
      "_resolved": "",
      "_integrity": "",
      "_from": "file:com.unity.toolchain.win-x86_64-linux-x86_64-0.1.13-preview.tgz",
      "readmeFilename": "README.md",
      "bugs": {
        "url": "https://github.com/Unity-Technologies/com.unity.sysroot/issues"
      },
      "homepage": "https://github.com/Unity-Technologies/com.unity.sysroot#readme",
      "_id": "com.unity.toolchain.win-x86_64-linux-x86_64@0.1.13-preview",
      "dist": {
        "shasum": "5bf93707919cb25dbf76f4d84d900e7ccddf9b0f",
        "tarball": "https://download-packages.unity.cn/com.unity.toolchain.win-x86_64-linux-x86_64/-/com.unity.toolchain.win-x86_64-linux-x86_64-0.1.13-preview.tgz"
      }
    },
    "0.1.11-preview": {
      "name": "com.unity.toolchain.win-x86_64-linux-x86_64",
      "version": "0.1.11-preview",
      "displayName": "Toolchain Win Linux x64",
      "description": "Cross-compilation toolchain to build player target Linux x86_64 on host Windows x86_64",
      "keywords": [
        "toolchain",
        "windows",
        "linux",
        "cross-compilation"
      ],
      "category": "",
      "dependencies": {
        "com.unity.sysroot": "0.1.12-preview",
        "com.unity.sysroot.linux-x86_64": "0.1.10-preview"
      },
      "unity": "2019.3",
      "author": {
        "name": "Unity Technologies Inc.",
        "url": "https://www.unity3d.com"
      },
      "upmCi": {
        "footprint": "5df787a235ee4cc60a2b5833d6d8851c98d40be6"
      },
      "repository": {
        "url": "git+https://github.com/Unity-Technologies/com.unity.sysroot.git",
        "type": "git",
        "revision": "2bfb535796029098235723b06450efd94adff446"
      },
      "_resolved": "",
      "_integrity": "",
      "_from": "file:com.unity.toolchain.win-x86_64-linux-x86_64-0.1.11-preview.tgz",
      "readmeFilename": "README.md",
      "bugs": {
        "url": "https://github.com/Unity-Technologies/com.unity.sysroot/issues"
      },
      "homepage": "https://github.com/Unity-Technologies/com.unity.sysroot#readme",
      "_id": "com.unity.toolchain.win-x86_64-linux-x86_64@0.1.11-preview",
      "dist": {
        "shasum": "1c3269f04f4d812705850dac18209403f0a223ee",
        "tarball": "https://download-packages.unity.cn/com.unity.toolchain.win-x86_64-linux-x86_64/-/com.unity.toolchain.win-x86_64-linux-x86_64-0.1.11-preview.tgz"
      }
    },
    "0.1.10-preview": {
      "name": "com.unity.toolchain.win-x86_64-linux-x86_64",
      "version": "0.1.10-preview",
      "displayName": "Toolchain Win Linux x64",
      "description": "Cross-compilation toolchain to build player target Linux x86_64 on host Windows x86_64",
      "keywords": [
        "toolchain",
        "windows",
        "linux",
        "cross-compilation"
      ],
      "category": "",
      "dependencies": {
        "com.unity.sysroot": "0.1.11-preview",
        "com.unity.sysroot.linux-x86_64": "0.1.9-preview"
      },
      "unity": "2019.3",
      "author": {
        "name": "Unity Technologies Inc.",
        "url": "https://www.unity3d.com"
      },
      "upmCi": {
        "footprint": "5871a335dfbe42298ce48d7b4dbe597f98447485"
      },
      "repository": {
        "url": "git+https://github.com/Unity-Technologies/com.unity.sysroot.git",
        "type": "git",
        "revision": "298c6f66b3f501f464fb4a97a0bcf3bd69366cfd"
      },
      "_resolved": "",
      "_integrity": "",
      "_from": "file:com.unity.toolchain.win-x86_64-linux-x86_64-0.1.10-preview.tgz",
      "readmeFilename": "README.md",
      "bugs": {
        "url": "https://github.com/Unity-Technologies/com.unity.sysroot/issues"
      },
      "homepage": "https://github.com/Unity-Technologies/com.unity.sysroot#readme",
      "_id": "com.unity.toolchain.win-x86_64-linux-x86_64@0.1.10-preview",
      "dist": {
        "shasum": "7978ca8c7646499cbfcf42ac2544e4e15cf050f6",
        "tarball": "https://download-packages.unity.cn/com.unity.toolchain.win-x86_64-linux-x86_64/-/com.unity.toolchain.win-x86_64-linux-x86_64-0.1.10-preview.tgz"
      }
    },
    "0.1.9-preview": {
      "name": "com.unity.toolchain.win-x86_64-linux-x86_64",
      "version": "0.1.9-preview",
      "displayName": "Toolchain Win Linux x64",
      "description": "Cross-compilation toolchain to build player target Linux x86_64 on host Windows x86_64",
      "keywords": [
        "toolchain",
        "windows",
        "linux",
        "cross-compilation"
      ],
      "category": "",
      "dependencies": {
        "com.unity.sysroot": "0.1.11-preview",
        "com.unity.sysroot.linux-x86_64": "0.1.9-preview"
      },
      "unity": "2019.3",
      "author": {
        "name": "Unity Technologies Inc.",
        "url": "https://www.unity3d.com"
      },
      "upmCi": {
        "footprint": "e3ac61f2908c14dda5cb4ed8c1574411751fc21d"
      },
      "repository": {
        "url": "git+https://github.com/Unity-Technologies/com.unity.sysroot.git",
        "type": "git",
        "revision": "90dfc0a0aa813ff749400d71ffd1755da46d2c83"
      },
      "_resolved": "",
      "_integrity": "",
      "_from": "file:com.unity.toolchain.win-x86_64-linux-x86_64-0.1.9-preview.tgz",
      "readmeFilename": "README.md",
      "bugs": {
        "url": "https://github.com/Unity-Technologies/com.unity.sysroot/issues"
      },
      "homepage": "https://github.com/Unity-Technologies/com.unity.sysroot#readme",
      "_id": "com.unity.toolchain.win-x86_64-linux-x86_64@0.1.9-preview",
      "dist": {
        "shasum": "08954193c09ab5b0b8c8f1fd813b9a5f919ac3a0",
        "tarball": "https://download-packages.unity.cn/com.unity.toolchain.win-x86_64-linux-x86_64/-/com.unity.toolchain.win-x86_64-linux-x86_64-0.1.9-preview.tgz"
      }
    },
    "0.1.8-preview": {
      "name": "com.unity.toolchain.win-x86_64-linux-x86_64",
      "version": "0.1.8-preview",
      "displayName": "Toolchain Win Linux x64",
      "description": "Cross-compilation toolchain to build player target Linux x86_64 on host Windows x86_64",
      "keywords": [
        "toolchain",
        "windows",
        "linux",
        "cross-compilation"
      ],
      "category": "",
      "dependencies": {
        "com.unity.sysroot": "0.1.10-preview",
        "com.unity.sysroot.linux-x86_64": "0.1.8-preview"
      },
      "unity": "2019.3",
      "author": {
        "name": "Unity Technologies Inc.",
        "url": "https://www.unity3d.com"
      },
      "upmCi": {
        "footprint": "080c28b12dd4dca2520487aaa5bbca865fb9a76e"
      },
      "repository": {
        "url": "git+https://github.com/Unity-Technologies/com.unity.sysroot.git",
        "type": "git",
        "revision": "05a3bdb214c46a4029ef107ce9114ac64415b2ba"
      },
      "_resolved": "",
      "_integrity": "",
      "_from": "file:com.unity.toolchain.win-x86_64-linux-x86_64-0.1.8-preview.tgz",
      "readmeFilename": "README.md",
      "bugs": {
        "url": "https://github.com/Unity-Technologies/com.unity.sysroot/issues"
      },
      "homepage": "https://github.com/Unity-Technologies/com.unity.sysroot#readme",
      "_id": "com.unity.toolchain.win-x86_64-linux-x86_64@0.1.8-preview",
      "dist": {
        "shasum": "7e67e8ea1c719da7432507b1486ade23a9b32939",
        "tarball": "https://download-packages.unity.cn/com.unity.toolchain.win-x86_64-linux-x86_64/-/com.unity.toolchain.win-x86_64-linux-x86_64-0.1.8-preview.tgz"
      }
    },
    "0.1.7-preview": {
      "name": "com.unity.toolchain.win-x86_64-linux-x86_64",
      "version": "0.1.7-preview",
      "displayName": "Toolchain Win Linux x64",
      "description": "Cross-compilation toolchain to build player target Linux x86_64 on host Windows x86_64",
      "keywords": [
        "toolchain",
        "windows",
        "linux",
        "cross-compilation"
      ],
      "category": "",
      "dependencies": {
        "com.unity.sysroot": "0.1.10-preview",
        "com.unity.sysroot.linux-x86_64": "0.1.8-preview"
      },
      "unity": "2019.3",
      "author": {
        "name": "Unity Technologies Inc.",
        "url": "https://www.unity3d.com"
      },
      "upmCi": {
        "footprint": "fb8e01a5d7263bb3052c407816359dfc9dc4fbfb"
      },
      "repository": {
        "url": "git+https://github.com/Unity-Technologies/com.unity.sysroot.git",
        "type": "git",
        "revision": "bef980a18593622191dc0ad150961f2cd95fb88f"
      },
      "_resolved": "",
      "_integrity": "",
      "_from": "file:com.unity.toolchain.win-x86_64-linux-x86_64-0.1.7-preview.tgz",
      "readmeFilename": "README.md",
      "bugs": {
        "url": "https://github.com/Unity-Technologies/com.unity.sysroot/issues"
      },
      "homepage": "https://github.com/Unity-Technologies/com.unity.sysroot#readme",
      "_id": "com.unity.toolchain.win-x86_64-linux-x86_64@0.1.7-preview",
      "dist": {
        "shasum": "11c5ac4504a2963dec9010af4d72406025029d79",
        "tarball": "https://download-packages.unity.cn/com.unity.toolchain.win-x86_64-linux-x86_64/-/com.unity.toolchain.win-x86_64-linux-x86_64-0.1.7-preview.tgz"
      }
    },
    "0.1.6-preview": {
      "name": "com.unity.toolchain.win-x86_64-linux-x86_64",
      "version": "0.1.6-preview",
      "displayName": "Toolchain Win Linux x64",
      "description": "Cross-compilation toolchain to build player target Linux x86_64 on host Windows x86_64",
      "keywords": [
        "toolchain",
        "windows",
        "linux",
        "cross-compilation"
      ],
      "category": "",
      "dependencies": {
        "com.unity.sysroot": "0.1.9-preview",
        "com.unity.sysroot.linux-x86_64": "0.1.8-preview"
      },
      "unity": "2019.3",
      "author": {
        "name": "Unity Technologies Inc.",
        "url": "https://www.unity3d.com"
      },
      "upmCi": {
        "footprint": "db254039a4e75435c49268b367df93ca5ca81911"
      },
      "repository": {
        "url": "git+https://github.com/Unity-Technologies/com.unity.sysroot.git",
        "type": "git",
        "revision": "0728ec6f89be9aeb3086ae0f2920cf7b075e6afc"
      },
      "_resolved": "",
      "_integrity": "",
      "_from": "file:com.unity.toolchain.win-x86_64-linux-x86_64-0.1.6-preview.tgz",
      "readmeFilename": "README.md",
      "bugs": {
        "url": "https://github.com/Unity-Technologies/com.unity.sysroot/issues"
      },
      "homepage": "https://github.com/Unity-Technologies/com.unity.sysroot#readme",
      "_id": "com.unity.toolchain.win-x86_64-linux-x86_64@0.1.6-preview",
      "dist": {
        "shasum": "678afe5c6ebb2656eb39d29cb368983db77097cb",
        "tarball": "https://download-packages.unity.cn/com.unity.toolchain.win-x86_64-linux-x86_64/-/com.unity.toolchain.win-x86_64-linux-x86_64-0.1.6-preview.tgz"
      }
    },
    "0.1.5-preview": {
      "name": "com.unity.toolchain.win-x86_64-linux-x86_64",
      "version": "0.1.5-preview",
      "displayName": "Toolchain Win Linux x64",
      "description": "Cross-compilation toolchain build player target Linux x86_64 on host Windows x86_64",
      "keywords": [
        "toolchain",
        "windows",
        "linux",
        "cross-compilation"
      ],
      "category": "",
      "dependencies": {
        "com.unity.sysroot": "0.1.8-preview",
        "com.unity.sysroot.linux-x86_64": "0.1.7-preview"
      },
      "unity": "2019.3",
      "author": {
        "name": "Unity",
        "url": "https://www.unity3d.com"
      },
      "upmCi": {
        "footprint": "066c73f94c380c88584124874b038a73550775a4"
      },
      "repository": {
        "url": "git+https://github.com/Unity-Technologies/com.unity.sysroot.git",
        "type": "git",
        "revision": "51d42010ec5c7735f037c6c079929866ade542f2"
      },
      "_resolved": "",
      "_integrity": "",
      "_from": "file:com.unity.toolchain.win-x86_64-linux-x86_64-0.1.5-preview.tgz",
      "readmeFilename": "README.md",
      "bugs": {
        "url": "https://github.com/Unity-Technologies/com.unity.sysroot/issues"
      },
      "homepage": "https://github.com/Unity-Technologies/com.unity.sysroot#readme",
      "_id": "com.unity.toolchain.win-x86_64-linux-x86_64@0.1.5-preview",
      "dist": {
        "shasum": "6b7a0a4f1a363b23a97798323dc0e993cf31c3f0",
        "tarball": "https://download-packages.unity.cn/com.unity.toolchain.win-x86_64-linux-x86_64/-/com.unity.toolchain.win-x86_64-linux-x86_64-0.1.5-preview.tgz"
      }
    },
    "0.1.4-preview": {
      "name": "com.unity.toolchain.win-x86_64-linux-x86_64",
      "version": "0.1.4-preview",
      "displayName": "Toolchain Win Linux x64",
      "description": "Cross-compilation toolchain build player target Linux x86_64 on host Windows x86_64",
      "keywords": [
        "toolchain",
        "windows",
        "linux",
        "cross-compilation"
      ],
      "dependencies": {
        "com.unity.sysroot": "0.1.7-preview",
        "com.unity.sysroot.linux-x86_64": "0.1.6-preview"
      },
      "unity": "2019.3",
      "author": {
        "name": "Unity",
        "url": "https://www.unity3d.com"
      },
      "upmCi": {
        "footprint": "38ba80ba3c5e892a1cf1d2b2be8a308f5811e9c0"
      },
      "repository": {
        "url": "git+https://github.com/Unity-Technologies/com.unity.sysroot.git",
        "type": "git",
        "revision": "174020d4f51d10fe5eef2238b69975643bddf4fc"
      },
      "_resolved": "",
      "_integrity": "",
      "_from": "file:C:/Users/BRIANR~1/AppData/Local/Temp/com.unity.toolchain.win-x86_64-linux-x86_64-0.1.4-preview.tgz",
      "readmeFilename": "README.md",
      "bugs": {
        "url": "https://github.com/Unity-Technologies/com.unity.sysroot/issues"
      },
      "homepage": "https://github.com/Unity-Technologies/com.unity.sysroot#readme",
      "_id": "com.unity.toolchain.win-x86_64-linux-x86_64@0.1.4-preview",
      "dist": {
        "shasum": "cb0a8159fba61d1dae7f4d0fcaa5e709810a8bdf",
        "tarball": "https://download-packages.unity.cn/com.unity.toolchain.win-x86_64-linux-x86_64/-/com.unity.toolchain.win-x86_64-linux-x86_64-0.1.4-preview.tgz"
      }
    }
  },
  "etag": "\"5907eb308eeceb0eaba530bfc2fb4393\"",
  "provider": "upm",
  "name": "com.unity.toolchain.win-x86_64-linux-x86_64",
  "description": "Cross-compilation toolchain to build player target Linux x86_64 on host Windows x86_64",
  "_id": "com.unity.toolchain.win-x86_64-linux-x86_64",
  "cnTags": [],
  "time": {
    "2.0.10": "2024-12-05T08:31:25Z",
    "2.0.9": "2024-04-30T08:52:38Z",
    "2.0.6": "2023-07-24T14:29:54Z",
    "2.0.5": "2023-05-09T12:46:49Z",
    "2.0.4": "2022-12-16T11:51:29Z",
    "2.0.3": "2022-11-10T12:43:33Z",
    "2.0.2": "2022-06-07T20:39:28Z",
    "2.0.1": "2022-05-06T18:37:15Z",
    "2.0.0": "2022-04-04T21:06:25Z",
    "1.0.0": "2022-01-07T10:51:39Z",
    "0.1.21-preview": "2021-07-15T19:28:58Z",
    "0.1.20-preview": "2021-05-03T04:15:42Z",
    "0.1.19-preview": "2021-02-24T09:15:16Z",
    "0.1.18-preview": "2021-01-12T18:11:51Z",
    "0.1.17-preview": "2020-11-29T04:23:01Z",
    "0.1.16-preview": "2020-11-10T12:39:24Z",
    "0.1.15-preview": "2020-11-05T21:57:51Z",
    "0.1.14-preview": "2020-09-30T07:07:44Z",
    "0.1.13-preview": "2020-09-23T19:03:17Z",
    "0.1.11-preview": "2020-09-08T09:57:59Z",
    "0.1.10-preview": "2020-09-04T06:25:39Z",
    "0.1.9-preview": "2020-08-27T08:08:58Z",
    "0.1.8-preview": "2020-08-26T23:26:45Z",
    "0.1.7-preview": "2020-08-21T20:33:43Z",
    "0.1.6-preview": "2020-07-16T00:40:55Z",
    "0.1.5-preview": "2020-06-18T18:20:51Z",
    "0.1.4-preview": "2020-05-26T16:56:51Z"
  }
}
